ui3/__init__.py
ui3/gestures.py
ui3/gridview.py
ui3/hierarchy.py
ui3/menu.py
ui3/pagecontrol.py
ui3/richlabel.py
ui3/safearea.py
ui3/sfsymbol.py
ui3/sfsymbol_browser.py
ui3/sfsymbolnames-2_1.json
ui3/sfsymbols-restricted-2_1.json
ui3/anchor/__init__.py
ui3/anchor/core.py
ui3/anchor/objc_plus.py
ui3/anchor/observer.py
ui3/anchor/safe_area.py
ui3-2021.1.10.dist-info/WHEEL
ui3-2021.1.10.dist-info/METADATA
ui3-2021.1.10.dist-info/RECORD
