Metadata-Version: 2.1
Name: ui3
Version: 2021.1.10
Summary: UI and other utils for Pythonista iOS app
Home-page: https://github.com/mikaelho/uiutils
License: TheUnlicense
Author: Mikael Honkala
Author-email: mikael.honkala@gmail.com
Classifier: Operating System :: iOS
